pirec/__init__.py
pirec/__version__.py
pirec/artefacts.py
pirec/environment.py
pirec/processresult.py
pirec/utils.py
pirec/recorders/__init__.py
pirec/recorders/csvfile.py
pirec/recorders/mongodb.py
pirec/recorders/slack.py
pirec/recorders/sqldatabase.py
pirec/recorders/stdout.py
pirec-0.11.0.dist-info/DESCRIPTION.rst
pirec-0.11.0.dist-info/METADATA
pirec-0.11.0.dist-info/RECORD
pirec-0.11.0.dist-info/WHEEL
pirec-0.11.0.dist-info/metadata.json
pirec-0.11.0.dist-info/top_level.txt
pirec-0.11.0.dist-info/zip-safe
